{"date": "2022-07-07", "topLanguages": [{"payload__pull_request__head__repo__language": "JavaScript", "count": 140176}, {"payload__pull_request__head__repo__language": "TypeScript", "count": 39531}, {"payload__pull_request__head__repo__language": "Java", "count": 24032}, {"payload__pull_request__head__repo__language": "HTML", "count": 22761}, {"payload__pull_request__head__repo__language": "CSS", "count": 16004}, {"payload__pull_request__head__repo__language": "Vue", "count": 15135}, {"payload__pull_request__head__repo__language": "Python", "count": 10745}, {"payload__pull_request__head__repo__language": "C#", "count": 8952}, {"payload__pull_request__head__repo__language": "PHP", "count": 6066}, {"payload__pull_request__head__repo__language": "Go", "count": 6007}, {"payload__pull_request__head__repo__language": "Ruby", "count": 3286}, {"payload__pull_request__head__repo__language": "C++", "count": 2628}, {"payload__pull_request__head__repo__language": "Kotlin", "count": 2279}, {"payload__pull_request__head__repo__language": "Shell", "count": 2025}, {"payload__pull_request__head__repo__language": "Scala", "count": 1875}, {"payload__pull_request__head__repo__language": "Jupyter Notebook", "count": 1779}, {"payload__pull_request__head__repo__language": "Rust", "count": 1702}, {"payload__pull_request__head__repo__language": "C", "count": 1516}, {"payload__pull_request__head__repo__language": "Roff", "count": 1453}, {"payload__pull_request__head__repo__language": "Julia", "count": 998}, {"payload__pull_request__head__repo__language": "SCSS", "count": 881}, {"payload__pull_request__head__repo__language": "Dart", "count": 699}, {"payload__pull_request__head__repo__language": "TSQL", "count": 653}, {"payload__pull_request__head__repo__language": "Dockerfile", "count": 631}, {"payload__pull_request__head__repo__language": "Swift", "count": 564}, {"payload__pull_request__head__repo__language": "HCL", "count": 528}, {"payload__pull_request__head__repo__language": "PowerShell", "count": 471}, {"payload__pull_request__head__repo__language": "Stylus", "count": 391}, {"payload__pull_request__head__repo__language": "EJS", "count": 383}, {"payload__pull_request__head__repo__language": "Makefile", "count": 333}], "topStarred": [{"repo__name": "Jarred-Sumner/bun", "count": 4385}, {"repo__name": "WongKinYiu/yolov7", "count": 758}, {"repo__name": "pocketbase/pocketbase", "count": 565}, {"repo__name": "OpenEthan/SMSBoom", "count": 445}, {"repo__name": "mtdvio/every-programmer-should-know", "count": 434}, {"repo__name": "Java-S12138/frank", "count": 403}, {"repo__name": "t3-oss/create-t3-app", "count": 382}, {"repo__name": "aplus-framework/app", "count": 314}, {"repo__name": "WerWolv/ImHex", "count": 299}, {"repo__name": "codecrafters-io/build-your-own-x", "count": 264}, {"repo__name": "sdras/awesome-actions", "count": 263}, {"repo__name": "facebookresearch/fairseq", "count": 252}, {"repo__name": "sindresorhus/awesome", "count": 217}, {"repo__name": "donnemartin/system-design-primer", "count": 204}, {"repo__name": "girliemac/a-picture-is-worth-a-1000-words", "count": 197}, {"repo__name": "kamranahmedse/developer-roadmap", "count": 187}, {"repo__name": "hemanth/functional-programming-jargon", "count": 185}, {"repo__name": "infracost/vscode-infracost", "count": 185}, {"repo__name": "ziglang/zig", "count": 184}, {"repo__name": "massCodeIO/massCode", "count": 182}, {"repo__name": "public-apis/public-apis", "count": 179}, {"repo__name": "aplus-framework/database", "count": 174}, {"repo__name": "sherlock-project/sherlock", "count": 169}, {"repo__name": "jinfagang/yolov7", "count": 167}, {"repo__name": "labring/laf", "count": 155}, {"repo__name": "microsoft/Web-Dev-For-Beginners", "count": 153}, {"repo__name": "railwayapp/nixpacks", "count": 151}, {"repo__name": "jwasham/coding-interview-university", "count": 137}, {"repo__name": "EbookFoundation/free-programming-books", "count": 135}, {"repo__name": "aplus-framework/cli", "count": 127}, {"repo__name": "sunface/rust-by-practice", "count": 126}, {"repo__name": "ossu/computer-science", "count": 123}, {"repo__name": "aplus-framework/pagination", "count": 123}, {"repo__name": "aplus-framework/http-client", "count": 122}, {"repo__name": "vinta/awesome-python", "count": 121}, {"repo__name": "babysor/MockingBird", "count": 118}, {"repo__name": "jaywcjlove/awesome-mac", "count": 117}, {"repo__name": "memester-xyz/surl", "count": 116}, {"repo__name": "aplus-framework/email", "count": 115}, {"repo__name": "KasperskyLab/TinyCheck", "count": 114}, {"repo__name": "CRED-CLUB/neopop-web", "count": 112}, {"repo__name": "aplus-framework/session", "count": 110}, {"repo__name": "aplus-framework/http", "count": 109}, {"repo__name": "yangshun/tech-interview-handbook", "count": 107}, {"repo__name": "aplus-framework/routing", "count": 106}, {"repo__name": "aplus-framework/one", "count": 106}, {"repo__name": "aplus-framework/framework", "count": 106}, {"repo__name": "citronneur/pamspy", "count": 105}, {"repo__name": "aplus-framework/image", "count": 104}, {"repo__name": "aplus-framework/aplus", "count": 102}, {"repo__name": "aplus-framework/validation", "count": 101}, {"repo__name": "Lee-WonJun/JDD-Description", "count": 100}, {"repo__name": "denoland/fresh", "count": 100}, {"repo__name": "tauri-apps/tauri", "count": 95}, {"repo__name": "facundoolano/software-papers", "count": 94}, {"repo__name": "aplus-framework/language", "count": 94}, {"repo__name": "TheAlgorithms/Python", "count": 94}, {"repo__name": "awesome-selfhosted/awesome-selfhosted", "count": 93}, {"repo__name": "30-seconds/30-seconds-of-code", "count": 91}, {"repo__name": "alexbieber/Bug_Bounty_writeups", "count": 89}, {"repo__name": "secretflow/secretflow", "count": 88}, {"repo__name": "lionsoul2014/ip2region", "count": 86}, {"repo__name": "aplus-framework/mvc", "count": 84}, {"repo__name": "pola-rs/polars", "count": 83}, {"repo__name": "mui/material-ui", "count": 82}, {"repo__name": "LeaVerou/color.js", "count": 79}, {"repo__name": "zilexa/Homeserver", "count": 79}, {"repo__name": "rustdesk/rustdesk", "count": 77}, {"repo__name": "meituan/YOLOv6", "count": 77}, {"repo__name": "soimort/you-get", "count": 76}, {"repo__name": "github/gitignore", "count": 75}, {"repo__name": "gogitdb/gitdb", "count": 73}, {"repo__name": "BrainJS/brain.js", "count": 73}, {"repo__name": "freeCodeCamp/freeCodeCamp", "count": 73}, {"repo__name": "sachaos/viddy", "count": 69}, {"repo__name": "trekhleb/javascript-algorithms", "count": 68}, {"repo__name": "type-challenges/type-challenges", "count": 68}, {"repo__name": "trpc/trpc", "count": 68}, {"repo__name": "bradtraversy/design-resources-for-developers", "count": 68}, {"repo__name": "focus-creative-games/hybridclr", "count": 67}, {"repo__name": "awesomekling/ladybird", "count": 67}, {"repo__name": "emqx/emqx", "count": 66}, {"repo__name": "chatwoot/chatwoot", "count": 66}, {"repo__name": "Snailclimb/JavaGuide", "count": 65}, {"repo__name": "itorr/eva-title", "count": 65}, {"repo__name": "yylive/YYEVA", "count": 65}, {"repo__name": "uzh-rpg/rpg_ultimate_slam_open", "count": 64}, {"repo__name": "YauhenKavalchuk/interview-questions", "count": 63}, {"repo__name": "pmndrs/zustand", "count": 62}, {"repo__name": "facebook/react", "count": 60}, {"repo__name": "LSPosed/MagiskOnWSA", "count": 60}, {"repo__name": "casey/just", "count": 59}, {"repo__name": "ultralytics/yolov5", "count": 58}, {"repo__name": "gothinkster/realworld", "count": 58}, {"repo__name": "trimstray/the-book-of-secret-knowledge", "count": 58}, {"repo__name": "borisdayma/dalle-mini", "count": 57}, {"repo__name": "h3xduck/TripleCross", "count": 56}, {"repo__name": "p0dalirius/Coercer", "count": 55}, {"repo__name": "google/google-ctf", "count": 55}, {"repo__name": "MeViMo/youbit", "count": 55}], "topStarredActive": [{"repo__name": "freeCodeCamp/freeCodeCamp", "count": 348689}, {"repo__name": "EbookFoundation/free-programming-books", "count": 238706}, {"repo__name": "jwasham/coding-interview-university", "count": 223770}, {"repo__name": "sindresorhus/awesome", "count": 207850}, {"repo__name": "kamranahmedse/developer-roadmap", "count": 199691}, {"repo__name": "vuejs/vue", "count": 197505}, {"repo__name": "facebook/react", "count": 190987}, {"repo__name": "tensorflow/tensorflow", "count": 166233}, {"repo__name": "twbs/bootstrap", "count": 158364}, {"repo__name": "flutter/flutter", "count": 142463}, {"repo__name": "TheAlgorithms/Python", "count": 139927}, {"repo__name": "github/gitignore", "count": 135107}, {"repo__name": "microsoft/vscode", "count": 133728}, {"repo__name": "vinta/awesome-python", "count": 132733}, {"repo__name": "Snailclimb/JavaGuide", "count": 124320}, {"repo__name": "facebook/react-native", "count": 103646}, {"repo__name": "electron/electron", "count": 102431}, {"repo__name": "golang/go", "count": 101358}, {"repo__name": "facebook/create-react-app", "count": 95839}, {"repo__name": "awesome-selfhosted/awesome-selfhosted", "count": 93754}, {"repo__name": "kubernetes/kubernetes", "count": 89974}, {"repo__name": "vercel/next.js", "count": 89244}, {"repo__name": "nodejs/node", "count": 88625}, {"repo__name": "microsoft/terminal", "count": 83904}, {"repo__name": "denoland/deno", "count": 83813}, {"repo__name": "mrdoob/three.js", "count": 83397}, {"repo__name": "angular/angular", "count": 82539}, {"repo__name": "microsoft/TypeScript", "count": 82064}, {"repo__name": "ant-design/ant-design", "count": 80981}, {"repo__name": "mui/material-ui", "count": 79635}, {"repo__name": "puppeteer/puppeteer", "count": 78864}, {"repo__name": "microsoft/PowerToys", "count": 74740}, {"repo__name": "tensorflow/models", "count": 73964}, {"repo__name": "storybookjs/storybook", "count": 72582}, {"repo__name": "rust-lang/rust", "count": 68483}, {"repo__name": "huggingface/transformers", "count": 66565}, {"repo__name": "vuejs/awesome-vue", "count": 65590}, {"repo__name": "bitcoin/bitcoin", "count": 65112}, {"repo__name": "django/django", "count": 64981}, {"repo__name": "moby/moby", "count": 63455}, {"repo__name": "opencv/opencv", "count": 62517}, {"repo__name": "spring-projects/spring-boot", "count": 62063}, {"repo__name": "sveltejs/svelte", "count": 60392}, {"repo__name": "elastic/elasticsearch", "count": 60272}, {"repo__name": "apple/swift", "count": 60036}, {"repo__name": "gohugoio/hugo", "count": 59963}, {"repo__name": "netdata/netdata", "count": 59849}, {"repo__name": "tailwindlabs/tailwindcss", "count": 58576}, {"repo__name": "reduxjs/redux", "count": 58329}, {"repo__name": "atom/atom", "count": 58258}, {"repo__name": "chartjs/Chart.js", "count": 57409}, {"repo__name": "mtdvio/every-programmer-should-know", "count": 57345}, {"repo__name": "pytorch/pytorch", "count": 57185}, {"repo__name": "ripienaar/free-for-dev", "count": 56288}, {"repo__name": "redis/redis", "count": 55830}, {"repo__name": "keras-team/keras", "count": 55603}, {"repo__name": "neovim/neovim", "count": 55378}, {"repo__name": "protocolbuffers/protobuf", "count": 55259}, {"repo__name": "home-assistant/core", "count": 53753}, {"repo__name": "ansible/ansible", "count": 53718}, {"repo__name": "gatsbyjs/gatsby", "count": 53188}, {"repo__name": "iptv-org/iptv", "count": 52853}, {"repo__name": "ElemeFE/element", "count": 52328}, {"repo__name": "apache/echarts", "count": 51624}, {"repo__name": "rails/rails", "count": 51039}, {"repo__name": "jaywcjlove/awesome-mac", "count": 50721}, {"repo__name": "scikit-learn/scikit-learn", "count": 50641}, {"repo__name": "godotengine/godot", "count": 50555}, {"repo__name": "grafana/grafana", "count": 49828}, {"repo__name": "enaqx/awesome-react", "count": 49017}, {"repo__name": "nestjs/nest", "count": 48430}, {"repo__name": "mermaid-js/mermaid", "count": 48290}, {"repo__name": "ionic-team/ionic-framework", "count": 47611}, {"repo__name": "apache/superset", "count": 46915}, {"repo__name": "TheAlgorithms/Java", "count": 46749}, {"repo__name": "strapi/strapi", "count": 46141}, {"repo__name": "google/material-design-icons", "count": 46093}, {"repo__name": "python/cpython", "count": 46052}, {"repo__name": "tauri-apps/tauri", "count": 46026}, {"repo__name": "syncthing/syncthing", "count": 45509}, {"repo__name": "google/guava", "count": 45055}, {"repo__name": "vitejs/vite", "count": 44008}, {"repo__name": "prettier/prettier", "count": 43279}, {"repo__name": "anuraghazra/github-readme-stats", "count": 43192}, {"repo__name": "serverless/serverless", "count": 43041}, {"repo__name": "meteor/meteor", "count": 42930}, {"repo__name": "git/git", "count": 42727}, {"repo__name": "square/okhttp", "count": 42438}, {"repo__name": "localstack/localstack", "count": 41969}, {"repo__name": "caddyserver/caddy", "count": 41508}, {"repo__name": "Solido/awesome-flutter", "count": 41456}, {"repo__name": "ColorlibHQ/AdminLTE", "count": 41154}, {"repo__name": "babel/babel", "count": 41079}, {"repo__name": "TryGhost/Ghost", "count": 40629}, {"repo__name": "etcd-io/etcd", "count": 40457}, {"repo__name": "gogs/gogs", "count": 40449}, {"repo__name": "v2ray/v2ray-core", "count": 39856}, {"repo__name": "microsoft/playwright", "count": 39845}, {"repo__name": "DefinitelyTyped/DefinitelyTyped", "count": 39827}, {"repo__name": "JuliaLang/julia", "count": 39785}], "topPullRequests": [{"repo__name": "WolseyBankWitness/rediffusion", "count": 1083}, {"repo__name": "mhutchinson/mhutchinson-distributor", "count": 837}, {"repo__name": "IT-xzy/Task", "count": 245}, {"repo__name": "google-test/signclav2-probe-repo", "count": 229}, {"repo__name": "JohnSnowLabs/spark-nlp", "count": 176}, {"repo__name": "trunk-test-02/mergequeue_service_test", "count": 162}, {"repo__name": "kdt-hphk/test-01", "count": 147}, {"repo__name": "actions-canary/ForkPRCanary", "count": 136}, {"repo__name": "NixOS/nixpkgs", "count": 136}, {"repo__name": "mergifyio-testing/functional-testing-repo", "count": 125}, {"repo__name": "Mpluya/config-tanzu-java-web-app-1-2", "count": 105}, {"repo__name": "microsoft/winget-pkgs", "count": 92}, {"repo__name": "killah-t-cell/NeuralPDE.jl", "count": 91}, {"repo__name": "GuruCICDCanary-Beta/CICDCanary", "count": 85}, {"repo__name": "avik-pal/FastDEQ.jl", "count": 84}, {"repo__name": "Programmer-RD-AI/Heart-Disease-UCI", "count": 82}, {"repo__name": "armorblox/dockerfiles", "count": 81}, {"repo__name": "codehaus/mule-git", "count": 81}, {"repo__name": "GuruCICDCanary-Prod/CICDCanary", "count": 78}, {"repo__name": "testbom1/datafab7", "count": 76}, {"repo__name": "GuruCICDCanary-Prod-Release/CICDCanary", "count": 72}, {"repo__name": "itsprivate/ts-new", "count": 72}, {"repo__name": "memetics19/Genie.jl", "count": 69}, {"repo__name": "anyframejava/anyframe-java-core", "count": 69}, {"repo__name": "Sun940201/SpringSpider", "count": 69}, {"repo__name": "Homebrew/homebrew-cask", "count": 68}, {"repo__name": "Programmer-RD-AI/Sign-Language-Recognition", "count": 66}, {"repo__name": "openshift-helm-charts/sandbox", "count": 62}, {"repo__name": "TechOffice/TechOffice-Java", "count": 62}, {"repo__name": "Programmer-RD-AI/Weather-Clf", "count": 62}, {"repo__name": "MaxMood96/google-api-nodejs-client", "count": 54}, {"repo__name": "poad/aws-example", "count": 54}, {"repo__name": "chriselrod/OrdinaryDiffEq.jl", "count": 53}, {"repo__name": "YEJUNG-LEE/EZ_HOME", "count": 52}, {"repo__name": "elastic/kibana", "count": 51}, {"repo__name": "gstein3m/OrdinaryDiffEq.jl", "count": 50}, {"repo__name": "aelmanaa/cl-docs", "count": 49}, {"repo__name": "getsentry/sentry", "count": 46}, {"repo__name": "WebKit/WebKit", "count": 46}, {"repo__name": "Programmer-RD-AI/House-Prices-Advanced-Regression-Techniques-V9-Competition", "count": 45}, {"repo__name": "marshall7m-testing/mut-terraform-aws-infrastructure-conftest", "count": 45}, {"repo__name": "stjordanis/OrdinaryDiffEq.jl", "count": 44}, {"repo__name": "grafana/grafana", "count": 44}, {"repo__name": "openshift/release", "count": 43}, {"repo__name": "sourcegraph/sourcegraph", "count": 43}, {"repo__name": "Homebrew/homebrew-core", "count": 42}, {"repo__name": "brianchandotcom/liferay-portal", "count": 42}, {"repo__name": "OCA/OpenUpgrade", "count": 42}, {"repo__name": "openshift/openshift-docs", "count": 40}, {"repo__name": "zephyrproject-rtos/zephyr", "count": 40}, {"repo__name": "sejalv/mlops-zoomcamp", "count": 40}, {"repo__name": "semgrep/test-end-to-end-app", "count": 39}, {"repo__name": "harness/harness-core-ui", "count": 39}, {"repo__name": "hmrc/build-and-deploy-canary-service", "count": 38}, {"repo__name": "openstax/rex-web", "count": 38}, {"repo__name": "MillironX/BioAlignments.jl", "count": 38}, {"repo__name": "itsprivate/ts2", "count": 37}, {"repo__name": "DenysVuika/developing-with-angular", "count": 37}, {"repo__name": "project-chip/connectedhomeip", "count": 36}, {"repo__name": "odoo/odoo", "count": 36}, {"repo__name": "MystenLabs/sui", "count": 36}, {"repo__name": "wsbforg4/atomist-docker-tutorial", "count": 35}, {"repo__name": "Kubika-gg/pull-shark-automation", "count": 35}, {"repo__name": "googleapis/google-cloud-ruby", "count": 35}, {"repo__name": "harness/harness-core", "count": 34}, {"repo__name": "apache/servicemix4-bundles", "count": 34}, {"repo__name": "stjordanis/ODE.jl", "count": 34}, {"repo__name": "smokey-org/atomist-docker-tutorial", "count": 34}, {"repo__name": "home-assistant/core", "count": 33}, {"repo__name": "andreamatos/primefaces-algaworks", "count": 33}, {"repo__name": "JuliaRegistries/General", "count": 31}, {"repo__name": "open-o11y/opentelemetry-collector-contrib", "count": 31}, {"repo__name": "planetarium/Flawless", "count": 31}, {"repo__name": "ajay2java2dev/source-fun", "count": 30}, {"repo__name": "testbom1/datafab6", "count": 30}, {"repo__name": "taosdata/TDengine", "count": 28}, {"repo__name": "tvttavares/java-EE-primefaces", "count": 28}, {"repo__name": "newjersey/navigator.business.nj.gov", "count": 27}, {"repo__name": "momodel/notebook", "count": 27}, {"repo__name": "cockroachdb/cockroach", "count": 27}, {"repo__name": "truecharts/containers", "count": 27}, {"repo__name": "ibm-developer-skills-network/jbbmo-Introduction-to-Git-and-GitHub", "count": 26}, {"repo__name": "turingschool-examples/school_challenge_2207", "count": 26}, {"repo__name": "mdn/content", "count": 26}, {"repo__name": "dotnet/roslyn", "count": 26}, {"repo__name": "earlhalasan/Project-3", "count": 26}, {"repo__name": "Noga-Zohar/Hackathon_2022", "count": 26}, {"repo__name": "choidongkuen/oss_project", "count": 25}, {"repo__name": "pytorch/pytorch", "count": 25}, {"repo__name": "lin09/demo", "count": 25}, {"repo__name": "ClickHouse/ClickHouse", "count": 25}, {"repo__name": "CodeCrowCorp/mvp-web-client", "count": 25}, {"repo__name": "pingcap/docs-cn", "count": 25}, {"repo__name": "apache/shardingsphere", "count": 25}, {"repo__name": "alfb1/core-java-serverfaces-3th", "count": 25}, {"repo__name": "Lv-704-TAQC-Java-project/CodeWars704", "count": 24}, {"repo__name": "khenheller/transition_detection", "count": 24}, {"repo__name": "janc-pxl/pxl-projectmanagement-doc", "count": 24}, {"repo__name": "kaisoul224/pull-shark-automation", "count": 24}, {"repo__name": "sanjeevi-mariappan/tutorials", "count": 24}]}