{"date": "2022-08-06", "topLanguages": [{"payload__pull_request__head__repo__language": "JavaScript", "count": 12476}, {"payload__pull_request__head__repo__language": "TypeScript", "count": 8444}, {"payload__pull_request__head__repo__language": "Python", "count": 7526}, {"payload__pull_request__head__repo__language": "Java", "count": 6934}, {"payload__pull_request__head__repo__language": "HTML", "count": 4246}, {"payload__pull_request__head__repo__language": "Go", "count": 2396}, {"payload__pull_request__head__repo__language": "C++", "count": 1906}, {"payload__pull_request__head__repo__language": "Roff", "count": 1776}, {"payload__pull_request__head__repo__language": "C#", "count": 1764}, {"payload__pull_request__head__repo__language": "PHP", "count": 1602}, {"payload__pull_request__head__repo__language": "Shell", "count": 1573}, {"payload__pull_request__head__repo__language": "Ruby", "count": 1440}, {"payload__pull_request__head__repo__language": "CSS", "count": 1328}, {"payload__pull_request__head__repo__language": "C", "count": 1229}, {"payload__pull_request__head__repo__language": "Kotlin", "count": 1192}, {"payload__pull_request__head__repo__language": "Jupyter Notebook", "count": 1173}, {"payload__pull_request__head__repo__language": "Julia", "count": 1122}, {"payload__pull_request__head__repo__language": "Rust", "count": 1086}, {"payload__pull_request__head__repo__language": "Vue", "count": 899}, {"payload__pull_request__head__repo__language": "Dart", "count": 543}, {"payload__pull_request__head__repo__language": "SCSS", "count": 427}, {"payload__pull_request__head__repo__language": "Scala", "count": 361}, {"payload__pull_request__head__repo__language": "HCL", "count": 327}, {"payload__pull_request__head__repo__language": "Swift", "count": 326}, {"payload__pull_request__head__repo__language": "PowerShell", "count": 258}, {"payload__pull_request__head__repo__language": "Lua", "count": 256}, {"payload__pull_request__head__repo__language": "Dockerfile", "count": 232}, {"payload__pull_request__head__repo__language": "Nix", "count": 215}, {"payload__pull_request__head__repo__language": "DM", "count": 187}, {"payload__pull_request__head__repo__language": "Jinja", "count": 131}], "topStarred": [{"repo__name": "stemrollerapp/stemroller", "count": 533}, {"repo__name": "toeverything/AFFiNE", "count": 529}, {"repo__name": "moyix/fauxpilot", "count": 511}, {"repo__name": "t3-oss/create-t3-app", "count": 239}, {"repo__name": "sofn-xyz/mailing", "count": 203}, {"repo__name": "serhack/pdf-diff", "count": 196}, {"repo__name": "kamranahmedse/developer-roadmap", "count": 193}, {"repo__name": "aplus-framework/app", "count": 190}, {"repo__name": "public-apis/public-apis", "count": 176}, {"repo__name": "carbon-language/carbon-lang", "count": 155}, {"repo__name": "kingToolbox/WindTerm", "count": 154}, {"repo__name": "facebookresearch/demucs", "count": 149}, {"repo__name": "nearform/lyra", "count": 149}, {"repo__name": "jwasham/coding-interview-university", "count": 149}, {"repo__name": "charmbracelet/gum", "count": 139}, {"repo__name": "codecrafters-io/build-your-own-x", "count": 139}, {"repo__name": "last-byte/PersistenceSniper", "count": 136}, {"repo__name": "sindresorhus/awesome", "count": 130}, {"repo__name": "tkashkin/Adwaita-for-Steam", "count": 125}, {"repo__name": "Asabeneh/30-Days-Of-JavaScript", "count": 124}, {"repo__name": "asosnovsky/Shortumation", "count": 124}, {"repo__name": "flutter/flutter", "count": 120}, {"repo__name": "jina-ai/discoart", "count": 118}, {"repo__name": "Textualize/textual", "count": 117}, {"repo__name": "WerWolv/ImHex", "count": 117}, {"repo__name": "PKUFlyingPig/cs-self-learning", "count": 109}, {"repo__name": "livebud/bud", "count": 106}, {"repo__name": "microsoft/PowerToys", "count": 106}, {"repo__name": "donnemartin/system-design-primer", "count": 105}, {"repo__name": "Asabeneh/30-Days-Of-Python", "count": 105}, {"repo__name": "vinta/awesome-python", "count": 103}, {"repo__name": "awesome-selfhosted/awesome-selfhosted", "count": 103}, {"repo__name": "bobalice7/PCS-Prediction", "count": 101}, {"repo__name": "chainsulting/Smart-Contract-Security-Audits", "count": 98}, {"repo__name": "oven-sh/bun", "count": 97}, {"repo__name": "agoraxyz/guild.xyz", "count": 96}, {"repo__name": "trimstray/the-book-of-secret-knowledge", "count": 96}, {"repo__name": "aplus-framework/database", "count": 95}, {"repo__name": "juliocesarfort/public-pentesting-reports", "count": 93}, {"repo__name": "EbookFoundation/free-programming-books", "count": 91}, {"repo__name": "ventoy/Ventoy", "count": 90}, {"repo__name": "nealmckee/penumbra", "count": 90}, {"repo__name": "jackfrued/Python-100-Days", "count": 85}, {"repo__name": "pbatard/rufus", "count": 85}, {"repo__name": "hackergrrl/art-of-readme", "count": 81}, {"repo__name": "tabler/tabler", "count": 76}, {"repo__name": "NVlabs/instant-ngp", "count": 75}, {"repo__name": "LSPosed/MagiskOnWSA", "count": 75}, {"repo__name": "NVIDIAGameWorks/kaolin-wisp", "count": 75}, {"repo__name": "matanolabs/matano", "count": 75}, {"repo__name": "google-research/multinerf", "count": 72}, {"repo__name": "sudheerj/reactjs-interview-questions", "count": 71}, {"repo__name": "ossu/computer-science", "count": 70}, {"repo__name": "Anjok07/ultimatevocalremovergui", "count": 70}, {"repo__name": "theonedev/onedev", "count": 69}, {"repo__name": "CodeEditApp/CodeEdit", "count": 67}, {"repo__name": "naraB/SensorRotation", "count": 66}, {"repo__name": "Eugeny/tabby", "count": 66}, {"repo__name": "aplus-framework/language", "count": 65}, {"repo__name": "julianbuettner/tcp-over-http", "count": 64}, {"repo__name": "nopjmp/Dionysus", "count": 64}, {"repo__name": "torvalds/linux", "count": 63}, {"repo__name": "aplus-framework/image", "count": 62}, {"repo__name": "aplus-framework/cli", "count": 62}, {"repo__name": "KilledByAPixel/JSONCrush", "count": 62}, {"repo__name": "practical-tutorials/project-based-learning", "count": 62}, {"repo__name": "elonlit/Genesis", "count": 62}, {"repo__name": "jorgef/engineeringladders", "count": 61}, {"repo__name": "iejMac/video2numpy", "count": 60}, {"repo__name": "trickest/cve", "count": 60}, {"repo__name": "getify/You-Dont-Know-JS", "count": 59}, {"repo__name": "UxxHans/Rainbow-Cats-Personal-WeChat-MiniProgram", "count": 59}, {"repo__name": "aplus-framework/framework", "count": 59}, {"repo__name": "LGUG2Z/helix-vim", "count": 58}, {"repo__name": "aplus-framework/pagination", "count": 58}, {"repo__name": "Dorukuz/Discord-Token-Generator", "count": 57}, {"repo__name": "trekhleb/javascript-algorithms", "count": 57}, {"repo__name": "acorn-io/acorn", "count": 57}, {"repo__name": "ohmyzsh/ohmyzsh", "count": 57}, {"repo__name": "BottleSome/AutoApiSecret", "count": 57}, {"repo__name": "AppFlowy-IO/AppFlowy", "count": 56}, {"repo__name": "avelino/awesome-go", "count": 56}, {"repo__name": "golang/go", "count": 56}, {"repo__name": "TideSec/GoBypassAV", "count": 55}, {"repo__name": "aplus-framework/email", "count": 55}, {"repo__name": "aplus-framework/http-client", "count": 55}, {"repo__name": "facebook/react", "count": 55}, {"repo__name": "valinet/ExplorerPatcher", "count": 55}, {"repo__name": "punk-security/dnsReaper", "count": 55}, {"repo__name": "facebookresearch/ParlAI", "count": 54}, {"repo__name": "google/paranoid_crypto", "count": 54}, {"repo__name": "peng-zhihui/HelloWord-Keyboard", "count": 54}, {"repo__name": "facebook/docusaurus", "count": 53}, {"repo__name": "Dinesh-Sowndar/flutter-iot-app-ui", "count": 53}, {"repo__name": "aplus-framework/aplus", "count": 53}, {"repo__name": "Alexey-T/CudaText", "count": 52}, {"repo__name": "beeyev/thumbor-php", "count": 52}, {"repo__name": "bruce2233/evnet", "count": 52}, {"repo__name": "gioui/gio", "count": 52}, {"repo__name": "aplus-framework/routing", "count": 52}], "topStarredActive": [{"repo__name": "freeCodeCamp/freeCodeCamp", "count": 351047}, {"repo__name": "EbookFoundation/free-programming-books", "count": 243709}, {"repo__name": "kamranahmedse/developer-roadmap", "count": 205074}, {"repo__name": "public-apis/public-apis", "count": 204214}, {"repo__name": "vuejs/vue", "count": 198398}, {"repo__name": "facebook/react", "count": 192774}, {"repo__name": "tensorflow/tensorflow", "count": 166905}, {"repo__name": "twbs/bootstrap", "count": 158859}, {"repo__name": "flutter/flutter", "count": 143281}, {"repo__name": "TheAlgorithms/Python", "count": 141074}, {"repo__name": "github/gitignore", "count": 136678}, {"repo__name": "vinta/awesome-python", "count": 136482}, {"repo__name": "microsoft/vscode", "count": 135035}, {"repo__name": "Snailclimb/JavaGuide", "count": 125937}, {"repo__name": "facebook/react-native", "count": 104147}, {"repo__name": "electron/electron", "count": 102946}, {"repo__name": "golang/go", "count": 102491}, {"repo__name": "facebook/create-react-app", "count": 96338}, {"repo__name": "justjavac/free-programming-books-zh_CN", "count": 94749}, {"repo__name": "kubernetes/kubernetes", "count": 90885}, {"repo__name": "vercel/next.js", "count": 90686}, {"repo__name": "nodejs/node", "count": 89297}, {"repo__name": "avelino/awesome-go", "count": 85313}, {"repo__name": "denoland/deno", "count": 84409}, {"repo__name": "microsoft/terminal", "count": 84401}, {"repo__name": "mrdoob/three.js", "count": 84148}, {"repo__name": "angular/angular", "count": 83083}, {"repo__name": "microsoft/TypeScript", "count": 82988}, {"repo__name": "ant-design/ant-design", "count": 81343}, {"repo__name": "mui/material-ui", "count": 80292}, {"repo__name": "puppeteer/puppeteer", "count": 79292}, {"repo__name": "rust-lang/rust", "count": 70353}, {"repo__name": "huggingface/transformers", "count": 67919}, {"repo__name": "vuejs/awesome-vue", "count": 65914}, {"repo__name": "bitcoin/bitcoin", "count": 65559}, {"repo__name": "django/django", "count": 65527}, {"repo__name": "moby/moby", "count": 63699}, {"repo__name": "opencv/opencv", "count": 63058}, {"repo__name": "gin-gonic/gin", "count": 61699}, {"repo__name": "webpack/webpack", "count": 61524}, {"repo__name": "sveltejs/svelte", "count": 61269}, {"repo__name": "elastic/elasticsearch", "count": 60648}, {"repo__name": "apple/swift", "count": 60256}, {"repo__name": "netdata/netdata", "count": 60155}, {"repo__name": "tailwindlabs/tailwindcss", "count": 59461}, {"repo__name": "pytorch/pytorch", "count": 57804}, {"repo__name": "chartjs/Chart.js", "count": 57718}, {"repo__name": "ripienaar/free-for-dev", "count": 56812}, {"repo__name": "neovim/neovim", "count": 56510}, {"repo__name": "keras-team/keras", "count": 55848}, {"repo__name": "home-assistant/core", "count": 54277}, {"repo__name": "ansible/ansible", "count": 54058}, {"repo__name": "iptv-org/iptv", "count": 53612}, {"repo__name": "godotengine/godot", "count": 51685}, {"repo__name": "rails/rails", "count": 51186}, {"repo__name": "scikit-learn/scikit-learn", "count": 50977}, {"repo__name": "grafana/grafana", "count": 50300}, {"repo__name": "nestjs/nest", "count": 49213}, {"repo__name": "tiangolo/fastapi", "count": 48024}, {"repo__name": "TheAlgorithms/Java", "count": 47153}, {"repo__name": "python/cpython", "count": 46724}, {"repo__name": "strapi/strapi", "count": 46715}, {"repo__name": "tesseract-ocr/tesseract", "count": 46161}, {"repo__name": "junegunn/fzf", "count": 46105}, {"repo__name": "lydiahallie/javascript-questions", "count": 46061}, {"repo__name": "vitejs/vite", "count": 45750}, {"repo__name": "hoppscotch/hoppscotch", "count": 45490}, {"repo__name": "google/guava", "count": 45294}, {"repo__name": "jekyll/jekyll", "count": 45096}, {"repo__name": "anuraghazra/github-readme-stats", "count": 44239}, {"repo__name": "prometheus/prometheus", "count": 43697}, {"repo__name": "prettier/prettier", "count": 43533}, {"repo__name": "square/okhttp", "count": 42627}, {"repo__name": "localstack/localstack", "count": 42609}, {"repo__name": "TryGhost/Ghost", "count": 40776}, {"repo__name": "etcd-io/etcd", "count": 40761}, {"repo__name": "microsoft/playwright", "count": 40754}, {"repo__name": "DefinitelyTyped/DefinitelyTyped", "count": 40215}, {"repo__name": "JuliaLang/julia", "count": 40059}, {"repo__name": "obsproject/obs-studio", "count": 40035}, {"repo__name": "iamkun/dayjs", "count": 39833}, {"repo__name": "tldr-pages/tldr", "count": 39748}, {"repo__name": "mozilla/pdf.js", "count": 39479}, {"repo__name": "Textualize/rich", "count": 38993}, {"repo__name": "ethereum/go-ethereum", "count": 38666}, {"repo__name": "pi-hole/pi-hole", "count": 38143}, {"repo__name": "apache/dubbo", "count": 37707}, {"repo__name": "pixijs/pixijs", "count": 37083}, {"repo__name": "chinese-poetry/chinese-poetry", "count": 36841}, {"repo__name": "facebook/docusaurus", "count": 36437}, {"repo__name": "supabase/supabase", "count": 36278}, {"repo__name": "discourse/discourse", "count": 36145}, {"repo__name": "fastlane/fastlane", "count": 35608}, {"repo__name": "commaai/openpilot", "count": 35523}, {"repo__name": "grpc/grpc", "count": 35170}, {"repo__name": "isocpp/CppCoreGuidelines", "count": 34991}, {"repo__name": "vuetifyjs/vuetify", "count": 34961}, {"repo__name": "pandas-dev/pandas", "count": 34775}, {"repo__name": "sherlock-project/sherlock", "count": 34640}, {"repo__name": "minio/minio", "count": 34483}], "topPullRequests": [{"repo__name": "WolseyBankWitness/rediffusion", "count": 1430}, {"repo__name": "mhutchinson/mhutchinson-distributor", "count": 1146}, {"repo__name": "dineshtripathi30/partnertapdemo-2", "count": 522}, {"repo__name": "google-test/signclav2-probe-repo", "count": 288}, {"repo__name": "trunk-test-02/mergequeue_service_test", "count": 274}, {"repo__name": "FoORK-Lab/achievements", "count": 243}, {"repo__name": "klu-cse-y21/git-for-good-c2", "count": 194}, {"repo__name": "actions-canary/ForkPRCanary", "count": 182}, {"repo__name": "NixOS/nixpkgs", "count": 148}, {"repo__name": "killah-t-cell/NeuralPDE.jl", "count": 117}, {"repo__name": "itsprivate/ts-new", "count": 101}, {"repo__name": "iftg7n/Test", "count": 98}, {"repo__name": "GuruCICDCanary-Prod-Release/CICDCanary", "count": 96}, {"repo__name": "GuruCICDCanary-Prod/CICDCanary", "count": 96}, {"repo__name": "GuruCICDCanary-Beta/CICDCanary", "count": 95}, {"repo__name": "memetics19/Genie.jl", "count": 92}, {"repo__name": "tsalm-pivotal/tap-gitops", "count": 89}, {"repo__name": "Homebrew/homebrew-cask", "count": 78}, {"repo__name": "aelmanaa/cl-docs", "count": 76}, {"repo__name": "knva/pull-shark-automation", "count": 75}, {"repo__name": "microsoft/winget-pkgs", "count": 74}, {"repo__name": "chriselrod/OrdinaryDiffEq.jl", "count": 72}, {"repo__name": "gstein3m/OrdinaryDiffEq.jl", "count": 69}, {"repo__name": "stjordanis/OrdinaryDiffEq.jl", "count": 66}, {"repo__name": "Oluwasetemi/altschool-opensource-names", "count": 66}, {"repo__name": "Programmer-RD-AI/House-Prices-Advanced-Regression-Techniques-V9-Competition", "count": 64}, {"repo__name": "openshift-helm-charts/sandbox", "count": 64}, {"repo__name": "mohamed2020m/esef", "count": 59}, {"repo__name": "ctmbr/artsy", "count": 55}, {"repo__name": "itsprivate/ts2", "count": 54}, {"repo__name": "StarRocks/starrocks", "count": 52}, {"repo__name": "JuliaRegistries/General", "count": 49}, {"repo__name": "semgrep/test-end-to-end-app", "count": 48}, {"repo__name": "hmrc/build-and-deploy-canary-service", "count": 48}, {"repo__name": "stjordanis/ODE.jl", "count": 46}, {"repo__name": "MillironX/BioAlignments.jl", "count": 44}, {"repo__name": "Miny1110/SemiProject", "count": 43}, {"repo__name": "Homebrew/homebrew-core", "count": 42}, {"repo__name": "JRetza/React-Node-FullStack---Multi-User-Blogging-Platform-with-SEO-1", "count": 40}, {"repo__name": "ylabio/react-webinar-2", "count": 36}, {"repo__name": "SinLess-Games/App", "count": 34}, {"repo__name": "pewpasta/pull-shark-automation", "count": 33}, {"repo__name": "ibm-developer-skills-network/jbbmo-Introduction-to-Git-and-GitHub", "count": 32}, {"repo__name": "taosdata/TDengine", "count": 32}, {"repo__name": "pfapi/cicd-template", "count": 31}, {"repo__name": "williamcurry1981/Auctus-pharma-group", "count": 28}, {"repo__name": "haiiliin/abqpy", "count": 28}, {"repo__name": "nevillionaire/AirBnB_clone", "count": 27}, {"repo__name": "CleverRaven/Cataclysm-DDA", "count": 27}, {"repo__name": "woowacourse-study/2022-lv3-algorithm-study", "count": 27}, {"repo__name": "Dangermouse87/juris-japan", "count": 26}, {"repo__name": "2022-FourSure/trails-frontend", "count": 26}, {"repo__name": "MikitaTsiarentsyeu/Md-PT1-54-22", "count": 26}, {"repo__name": "ExelenterSDET/JavaCourse", "count": 26}, {"repo__name": "Shashankreddysunkara/saas", "count": 26}, {"repo__name": "dkw99/home-ops", "count": 26}, {"repo__name": "Emiller88/home-cluster", "count": 26}, {"repo__name": "DouglasGorges/purespectrum", "count": 25}, {"repo__name": "opengoofy/hippo4j", "count": 25}, {"repo__name": "newtonliu0/nl-event", "count": 24}, {"repo__name": "Mara-Li/Mara-Li", "count": 24}, {"repo__name": "FrozenWasabi/befunny", "count": 24}, {"repo__name": "D-Planner/data", "count": 24}, {"repo__name": "space-wizards/space-station-14", "count": 24}, {"repo__name": "datadesk/california-coronavirus-scrapers", "count": 24}, {"repo__name": "Homebrew/homebrew-cask-fonts", "count": 24}, {"repo__name": "lucidph3nx/home-ops", "count": 24}, {"repo__name": "MJPeppersdev/mjpeppersdev", "count": 23}, {"repo__name": "AjmalShajahan/AjmalShajahan", "count": 23}, {"repo__name": "emiakqa/Git-Workshop-A", "count": 23}, {"repo__name": "yewalenikhil65/MethodOfLines.jl", "count": 23}, {"repo__name": "rutvij-25/Metalhead.jl", "count": 23}, {"repo__name": "EncasedAmber/docs", "count": 23}, {"repo__name": "stjordanis/DifferentialEquations.jl", "count": 22}, {"repo__name": "Makzumm/goit-team-project", "count": 22}, {"repo__name": "mdn/content", "count": 22}, {"repo__name": "gjuchault/typescript-functional-service-starter", "count": 22}, {"repo__name": "firstcontributions/first-contributions", "count": 22}, {"repo__name": "msucorey/aawork", "count": 22}, {"repo__name": "keqingyuan/linkerd2", "count": 21}, {"repo__name": "Crafty-Tukka/crafty-tukka-frontend", "count": 21}, {"repo__name": "wowsims/wotlk", "count": 21}, {"repo__name": "ashimdahal/FRIDA-TEAM_AIR-KU-hackfest", "count": 21}, {"repo__name": "sthagen/nhn-tui.editor", "count": 21}, {"repo__name": "ayeh6/Offload", "count": 21}, {"repo__name": "mtwence/lets-play", "count": 21}, {"repo__name": "snyk-matt/goof-platform", "count": 21}, {"repo__name": "brocoders/nestjs-boilerplate", "count": 21}, {"repo__name": "rm3l/rm3l.org", "count": 21}, {"repo__name": "kurtabegnalle/dependabot-core", "count": 21}, {"repo__name": "dariahalai/parcel-team", "count": 20}, {"repo__name": "Pavelkalininn/fastapi_telegram_bot_ci_cd", "count": 20}, {"repo__name": "Mkish420/CarbonCombaters", "count": 20}, {"repo__name": "VitRod/Shopping-cart-site-spring-boot", "count": 20}, {"repo__name": "ballerina-platform/ballerina-performance-cloud", "count": 20}, {"repo__name": "Py4Js/PyScript-React", "count": 20}, {"repo__name": "nomunomu0504/covid19", "count": 20}, {"repo__name": "GeekOfProgramming/webpack", "count": 20}, {"repo__name": "albinou/albinou.github.io", "count": 20}, {"repo__name": "s-oo/SubProject", "count": 20}]}